{
    "default": {
        "PITCH0": {
            "blue": {
                "max": [
                    122, 
                    255, 
                    255
                ], 
                "min": [
                    102, 
                    140, 
                    140
                ]
            }, 
            "pink": {
                "max": [
                    171, 
                    255, 
                    255
                ], 
                "min": [
                    151, 
                    140, 
                    140
                ]
            }, 
            "maroon": {
                "max": [
                    180, 
                    255, 
                    255
                ], 
                "min": [
                    175, 
                    190, 
                    190
                ]
            }, 
            "green": {
                "max": [
                    68, 
                    255, 
                    255
                ], 
                "min": [
                    48, 
                    140, 
                    140
                ]
            }, 
            "yellow": {
                "max": [
                    46, 
                    255, 
                    255
                ], 
                "min": [
                    26, 
                    140, 
                    140
                ]
            }, 
            "bright_blue": {
                "max": [
                    105, 
                    255, 
                    255
                ], 
                "min": [
                    85, 
                    140, 
                    140
                ]
            }, 
            "red": {
                "max": [
                    5, 
                    255, 
                    255
                ], 
                "min": [
                    0, 
                    190, 
                    190
                ]
            }
        }, 
        "PITCH1": {
            "blue": {
                "erode": 0.0, 
                "min": [
                    68.0, 
                    98.0, 
                    71.0
                ], 
                "max": [
                    118.0, 
                    155.0, 
                    88.0
                ], 
                "highpass": 0.0, 
                "blur": 0, 
                "close": 0.0, 
                "open": 0.0, 
                "contrast": 0.0
            }, 
            "red": {
                "erode": 0.0, 
                "min": [
                    0.0, 
                    0.0, 
                    196.0
                ], 
                "max": [
                    7.0, 
                    237.0, 
                    255.0
                ], 
                "highpass": 0.0, 
                "blur": 7, 
                "close": 0.0, 
                "open": 0.0, 
                "contrast": 0.0
            }, 
            "yellow": {
                "erode": 0.0, 
                "min": [
                    16.0, 
                    165.0, 
                    136.0
                ], 
                "max": [
                    98.0, 
                    255.0, 
                    255.0
                ], 
                "blur": 0, 
                "close": 0, 
                "open": 0.0, 
                "contrast": 1.0
            }
        }
    }, 
    "glenorchy": {
        "PITCH0": {
            "blue": {
                "erode": 0.0, 
                "min": [
                    68.0, 
                    98.0, 
                    71.0
                ], 
                "max": [
                    118.0, 
                    155.0, 
                    88.0
                ], 
                "blur": 0, 
                "close": 0, 
                "open": 0.0, 
                "contrast": 0.0
            }, 
            "plate": {
                "erode": 0.0, 
                "min": [
                    45.0, 
                    56.0, 
                    189.0
                ], 
                "max": [
                    94.0, 
                    176.0, 
                    236.0
                ], 
                "blur": 5, 
                "close": 0, 
                "open": 0.0, 
                "contrast": 87.0
            }, 
            "dot": {
                "erode": 0.0, 
                "min": [
                    6.0, 
                    23.0, 
                    154.0
                ], 
                "max": [
                    94.0, 
                    63.0, 
                    170.0
                ], 
                "blur": 1, 
                "close": 0, 
                "open": 0.0, 
                "contrast": 100.0
            }, 
            "red": {
                "erode": 0.0, 
                "min": [
                    117.0, 
                    162.0, 
                    91.0
                ], 
                "max": [
                    188.0, 
                    255.0, 
                    237.0
                ], 
                "blur": 0, 
                "close": 0, 
                "open": 0.0, 
                "contrast": 0.0
            }, 
            "yellow": {
                "erode": 0.0, 
                "min": [
                    16.0, 
                    165.0, 
                    136.0
                ], 
                "max": [
                    98.0, 
                    255.0, 
                    255.0
                ], 
                "blur": 0, 
                "close": 0, 
                "open": 0.0, 
                "contrast": 1.0
            }
        }, 
        "PITCH1": {
            "blue": {
                "erode": 0.0, 
                "min": [
                    68.0, 
                    98.0, 
                    71.0
                ], 
                "max": [
                    118.0, 
                    155.0, 
                    88.0
                ], 
                "blur": 0, 
                "close": 0, 
                "open": 0.0, 
                "contrast": 0.0
            }, 
            "plate": {
                "erode": 0.0, 
                "min": [
                    49.0, 
                    64.0, 
                    214.0
                ], 
                "max": [
                    360.0, 
                    200.0, 
                    255.0
                ], 
                "blur": 5, 
                "close": 2.0, 
                "open": 3.0, 
                "contrast": 77.0
            }, 
            "yellow": {
                "erode": 0.0, 
                "min": [
                    16.0, 
                    165.0, 
                    136.0
                ], 
                "max": [
                    98.0, 
                    255.0, 
                    255.0
                ], 
                "blur": 0, 
                "close": 0, 
                "open": 0.0, 
                "contrast": 1.0
            }, 
            "red": {
                "erode": 0.0, 
                "min": [
                    0.0, 
                    0.0, 
                    196.0
                ], 
                "max": [
                    10.0, 
                    237.0, 
                    255.0
                ], 
                "blur": 7, 
                "close": 0.0, 
                "open": 3.0, 
                "contrast": 0.0
            }, 
            "dot": {
                "erode": 1.0, 
                "min": [
                    25.0, 
                    0.0, 
                    149.0
                ], 
                "max": [
                    68.0, 
                    87.0, 
                    199.0
                ], 
                "blur": 0, 
                "close": 2.0, 
                "open": 2.0, 
                "contrast": 100.0
            }
        }
    }, 
    "Dovile": {
        "PITCH0": {
            "blue": {
                "max": [
                    121, 
                    255, 
                    255
                ], 
                "min": [
                    101, 
                    123, 
                    160
                ]
            }, 
            "pink": {
                "max": [
                    171, 
                    255, 
                    255
                ], 
                "min": [
                    151, 
                    103, 
                    164
                ]
            }, 
            "maroon": {
                "max": [
                    180, 
                    255, 
                    255
                ], 
                "min": [
                    175, 
                    120, 
                    147
                ]
            }, 
            "green": {
                "max": [
                    62, 
                    255, 
                    255
                ], 
                "min": [
                    54, 
                    111, 
                    186
                ]
            }, 
            "yellow": {
                "max": [
                    44, 
                    255, 
                    255
                ], 
                "min": [
                    24, 
                    96, 
                    140
                ]
            }, 
            "bright_blue": {
                "max": [
                    106, 
                    255, 
                    255
                ], 
                "min": [
                    86, 
                    102, 
                    155
                ]
            }, 
            "red": {
                "max": [
                    5, 
                    255, 
                    255
                ], 
                "min": [
                    0, 
                    133, 
                    156
                ]
            }
        }, 
        "PITCH1": {
            "blue": {
                "erode": 0.0, 
                "min": [
                    68.0, 
                    98.0, 
                    71.0
                ], 
                "max": [
                    118.0, 
                    155.0, 
                    88.0
                ], 
                "highpass": 0.0, 
                "blur": 0, 
                "close": 0.0, 
                "open": 0.0, 
                "contrast": 0.0
            }, 
            "red": {
                "erode": 0.0, 
                "min": [
                    0.0, 
                    0.0, 
                    196.0
                ], 
                "max": [
                    7.0, 
                    237.0, 
                    255.0
                ], 
                "highpass": 0.0, 
                "blur": 7, 
                "close": 0.0, 
                "open": 0.0, 
                "contrast": 0.0
            }, 
            "yellow": {
                "erode": 0.0, 
                "min": [
                    16.0, 
                    165.0, 
                    136.0
                ], 
                "max": [
                    98.0, 
                    255.0, 
                    255.0
                ], 
                "blur": 0, 
                "close": 0, 
                "open": 0.0, 
                "contrast": 1.0
            }
        }
    }
}